{
  "release": {
    "description": "Releases",
    "hide": false,
    "last_updated": "2025-07-23T06:21:37.000Z",
    "last_updated_url": "https://github.com/hotio/jackett/actions/runs/16463094336",
    "latest": true,
    "tags": [
      "release",
      "release-0.22.2185",
      "release-830121a"
    ]
  },
  "testing": {
    "description": "Pre-releases",
    "hide": false,
    "last_updated": "2025-07-23T06:21:04.000Z",
    "last_updated_url": "https://github.com/hotio/jackett/actions/runs/16463094635",
    "latest": false,
    "tags": [
      "testing",
      "testing-0.22.2185",
      "testing-94f53dd"
    ]
  }
}
