{
  "release": {
    "description": "Releases",
    "hide": false,
    "last_updated": "2025-12-16T06:21:38.000Z",
    "last_updated_url": "https://github.com/hotio/jackett/actions/runs/20258563285",
    "latest": true,
    "tags": [
      "release",
      "release-0.24.457",
      "release-90cb5ec"
    ]
  },
  "testing": {
    "description": "Pre-releases",
    "hide": false,
    "last_updated": "2025-12-15T13:44:12.000Z",
    "last_updated_url": "https://github.com/hotio/jackett/actions/runs/20233973764",
    "latest": false,
    "tags": [
      "testing",
      "testing-0.24.454",
      "testing-a693221"
    ]
  }
}
