{
  "release": {
    "description": "Releases",
    "hide": false,
    "last_updated": "2024-06-07T16:26:59.000Z",
    "last_updated_url": "https://github.com/hotio/jackett/actions/runs/9419990977",
    "latest": true,
    "tags": [
      "release",
      "release-0.22.76",
      "release-44b43ce"
    ]
  },
  "testing": {
    "description": "Pre-releases",
    "hide": false,
    "last_updated": "2024-06-08T06:12:37.000Z",
    "last_updated_url": "https://github.com/hotio/jackett/actions/runs/9426717063",
    "latest": false,
    "tags": [
      "testing",
      "testing-0.22.84",
      "testing-e65a397"
    ]
  }
}
