{
  "release": {
    "description": "Releases",
    "hide": false,
    "last_updated": "2025-12-21T05:20:57.000Z",
    "last_updated_url": "https://github.com/hotio/jackett/actions/runs/20405075424",
    "latest": true,
    "tags": [
      "release",
      "release-0.24.488",
      "release-e51315e"
    ]
  },
  "testing": {
    "description": "Pre-releases",
    "hide": false,
    "last_updated": "2025-12-21T05:25:05.000Z",
    "last_updated_url": "https://github.com/hotio/jackett/actions/runs/20405075880",
    "latest": false,
    "tags": [
      "testing",
      "testing-0.24.488",
      "testing-f7a8e45"
    ]
  }
}
