{
  "release": {
    "description": "Releases",
    "hide": false,
    "last_updated": "2024-08-13T06:15:28.000Z",
    "last_updated_url": "https://github.com/hotio/jackett/actions/runs/10364562051",
    "latest": true,
    "tags": [
      "release",
      "release-0.22.442",
      "release-43e1f8b"
    ]
  },
  "testing": {
    "description": "Pre-releases",
    "hide": false,
    "last_updated": "2024-08-12T06:15:44.000Z",
    "last_updated_url": "https://github.com/hotio/jackett/actions/runs/10346814064",
    "latest": false,
    "tags": [
      "testing",
      "testing-0.22.439",
      "testing-5663039"
    ]
  }
}
