{
  "release": {
    "description": "Releases",
    "hide": false,
    "last_updated": "2025-12-23T13:40:51.000Z",
    "last_updated_url": "https://github.com/hotio/jackett/actions/runs/20461993845",
    "latest": true,
    "tags": [
      "release",
      "release-0.24.512",
      "release-6a78234"
    ]
  },
  "testing": {
    "description": "Pre-releases",
    "hide": false,
    "last_updated": "2025-12-23T13:41:33.000Z",
    "last_updated_url": "https://github.com/hotio/jackett/actions/runs/20461994402",
    "latest": false,
    "tags": [
      "testing",
      "testing-0.24.512",
      "testing-048a9f4"
    ]
  }
}
