{
  "release": {
    "description": "Releases",
    "hide": false,
    "last_updated": "2024-09-27T06:17:22.000Z",
    "last_updated_url": "https://github.com/hotio/jackett/actions/runs/11065511346",
    "latest": true,
    "tags": [
      "release",
      "release-0.22.681",
      "release-af25067"
    ]
  },
  "testing": {
    "description": "Pre-releases",
    "hide": false,
    "last_updated": "2024-09-28T06:14:27.000Z",
    "last_updated_url": "https://github.com/hotio/jackett/actions/runs/11081679485",
    "latest": false,
    "tags": [
      "testing",
      "testing-0.22.685",
      "testing-8036f0f"
    ]
  }
}
